vllm_plugin_meralion2/__init__.py
vllm_plugin_meralion2/vllm064_post1.py
vllm_plugin_meralion2/vllm085.py
vllm_plugin_meralion2/transformers_utils/__init__.py
vllm_plugin_meralion2/transformers_utils/configuration_meralion2.py
vllm_plugin_meralion2/transformers_utils/modules.py
vllm_plugin_meralion2/transformers_utils/no_repeat_logits_processor.py
vllm_plugin_meralion2/transformers_utils/processing_meralion2.py
vllm_plugin_meralion2-0.1.2.post2.dist-info/METADATA
vllm_plugin_meralion2-0.1.2.post2.dist-info/WHEEL
vllm_plugin_meralion2-0.1.2.post2.dist-info/entry_points.txt
vllm_plugin_meralion2-0.1.2.post2.dist-info/top_level.txt
vllm_plugin_meralion2-0.1.2.post2.dist-info/RECORD
