Metadata-Version: 2.4
Name: vllm_plugin_meralion2
Version: 0.1.2.post2
Summary: A vLLM plugin to register the MERaLiON-2-10B model architecture with vLLM’s plugin system.
Author: MERaLiON Team
Project-URL: Modelpage, https://huggingface.co/MERaLiON/MERaLiON-2-10B
Project-URL: Homepage, https://huggingface.co/MERaLiON/MERaLiON-2-10B/tree/main/vllm_plugin_meralion2
Project-URL: Documentation, https://huggingface.co/MERaLiON/MERaLiON-2-10B/blob/main/vllm_plugin_meralion2/readme.md
Requires-Python: >=3.9
Requires-Dist: transformers==4.50.1
Requires-Dist: librosa
